uforge/__init__.py
uforge/application.py
uforge/config/config.cfg
uforge/objects/__init__.py
uforge/objects/uforge.py
uforge_python_sdk-3.8.13.dist-info/DESCRIPTION.rst
uforge_python_sdk-3.8.13.dist-info/METADATA
uforge_python_sdk-3.8.13.dist-info/RECORD
uforge_python_sdk-3.8.13.dist-info/WHEEL
uforge_python_sdk-3.8.13.dist-info/metadata.json
uforge_python_sdk-3.8.13.dist-info/top_level.txt
