Metadata-Version: 2.0
Name: uforge-python-sdk
Version: 3.8.13
Summary: UForge python SDK
Home-page: UNKNOWN
Author: UShareSoft
Author-email: contact@usharesoft.com
License: Apache License 2.0
Platform: UNKNOWN
Classifier: Development Status :: 4 - Beta
Classifier: Topic :: Software Development :: Libraries
Classifier: Intended Audience :: Developers
Classifier: Intended Audience :: System Administrators
Classifier: Natural Language :: English
Classifier: Operating System :: MacOS :: MacOS X
Classifier: Operating System :: Microsoft :: Windows
Classifier: Operating System :: POSIX
Classifier: License :: OSI Approved :: Apache Software License
Classifier: Programming Language :: Python
Classifier: Programming Language :: Python :: 2.6
Classifier: Programming Language :: Python :: 2.7
Requires-Dist: lxml (==3.3.5)
Requires-Dist: pyxb (==1.2.4)
Requires-Dist: requests (==2.13.0)
